{
 "casa": "betano",
 "ok": true,
 "ts_utc": "2026-07-17T23:09:38Z",
 "ts_brt": "2026-07-17 20:09",
 "n_events": 60,
 "n_markets": 9,
 "market_counts": {
  "Cartões": 12,
  "Chutes no gol": 11,
  "Desarmes": 3,
  "Escanteios": 40,
  "Faltas": 9,
  "Finalizações": 11,
  "Impedimentos": 9,
  "Laterais": 3,
  "Tiros de meta": 3
 },
 "min_events": 15,
 "duration_sec": 575.8,
 "error": null,
 "error_class": null,
 "mode": "full",
 "sample_events": [],
 "proxy_br": true,
 "pointer_valid": true,
 "pointer_file": "betano_2026-07-17_2000.jsonl",
 "pointer_at": "2026-07-17T20:00:04-03:00",
 "pointer_age_h": 0.16
}