{"gerado": "2026-07-24 04:50", "n": 339, "rejects": [{"casa": "bet365", "mercado": "Escanteios", "linha": 5.0, "reason": "margin_low", "margin": -0.0066}, {"casa": "bet365", "mercado": "Escanteios", "linha": 6.0, "reason": "margin_low", "margin": -0.0342}, {"casa": "bet365", "mercado": "Escanteios", "linha": 7.0, "reason": "margin_low", "margin": -0.0308}, {"casa": "bet365", "mercado": "Escanteios", "linha": 8.0, "reason": "margin_low", "margin": -0.0523}, {"casa": "bet365", "mercado": "Escanteios", "linha": 10.0, "reason": "margin_low", "margin": -0.0444}, {"casa": "bet365", "mercado": "Escanteios", "linha": 11.0, "reason": "margin_low", "margin": -0.0476}, {"casa": "bet365", "mercado": "Escanteios", "linha": 12.0, "reason": "margin_low", "margin": -0.0188}, {"casa": "bet365", "mercado": "Escanteios", "linha": 13.0, "reason": "margin_low", "margin": -0.0024}, {"casa": "bet365", "mercado": "Escanteios", "linha": 6.0, "reason": "margin_low", "margin": -0.0162}, {"casa": "bet365", "mercado": "Escanteios", "linha": 7.0, "reason": "margin_low", "margin": -0.0333}, {"casa": "bet365", "mercado": "Escanteios", "linha": 8.0, "reason": "margin_low", "margin": -0.0389}, {"casa": "bet365", "mercado": "Escanteios", "linha": 9.0, "reason": "margin_low", "margin": -0.0403}, {"casa": "bet365", "mercado": "Escanteios", "linha": 11.0, "reason": "margin_low", "margin": -0.0455}, {"casa": "bet365", "mercado": "Escanteios", "linha": 12.0, "reason": "margin_low", "margin": -0.0147}, {"casa": "bet365", "mercado": "Escanteios", "linha": 13.0, "reason": "margin_low", "margin": -0.0137}, {"casa": "bet365", "mercado": "Escanteios", "linha": 5.0, "reason": "margin_low", "margin": -0.014}, {"casa": "bet365", "mercado": "Escanteios", "linha": 6.0, "reason": "margin_low", "margin": -0.0375}, {"casa": "bet365", "mercado": "Escanteios", "linha": 7.0, "reason": "margin_low", "margin": -0.0357}, {"casa": "bet365", "mercado": "Escanteios", "linha": 8.0, "reason": "margin_low", "margin": -0.0583}, {"casa": "bet365", "mercado": "Escanteios", "linha": 10.0, "reason": "margin_low", "margin": -0.0455}, {"casa": "bet365", "mercado": "Escanteios", "linha": 11.0, "reason": "margin_low", "margin": -0.0338}, {"casa": "bet365", "mercado": "Escanteios", "linha": 12.0, "reason": "margin_low", "margin": -0.0128}, {"casa": "bet365", "mercado": "Escanteios", "linha": 5.0, "reason": "margin_low", "margin": -0.0066}, {"casa": "bet365", "mercado": "Escanteios", "linha": 6.0, "reason": "margin_low", "margin": -0.0342}, {"casa": "bet365", "mercado": "Escanteios", "linha": 7.0, "reason": "margin_low", "margin": -0.0308}, {"casa": "bet365", "mercado": "Escanteios", "linha": 8.0, "reason": "margin_low", "margin": -0.0523}, {"casa": "bet365", "mercado": "Escanteios", "linha": 10.0, "reason": "margin_low", "margin": -0.0444}, {"casa": "bet365", "mercado": "Escanteios", "linha": 11.0, "reason": "margin_low", "margin": -0.0476}, {"casa": "bet365", "mercado": "Escanteios", "linha": 12.0, "reason": "margin_low", "margin": -0.0188}, {"casa": "bet365", "mercado": "Escanteios", "linha": 13.0, "reason": "margin_low", "margin": -0.0024}, {"casa": "bet365", "mercado": "Escanteios", "linha": 8.0, "reason": "margin_low", "margin": -0.0228}, {"casa": "bet365", "mercado": "Escanteios", "linha": 9.0, "reason": "margin_low", "margin": -0.0182}, {"casa": "bet365", "mercado": "Escanteios", "linha": 10.0, "reason": "margin_low", "margin": -0.019}, {"casa": "bet365", "mercado": "Escanteios", "linha": 11.0, "reason": "margin_low", "margin": -0.0376}, {"casa": "bet365", "mercado": "Escanteios", "linha": 13.0, "reason": "margin_low", "margin": -0.0403}, {"casa": "bet365", "mercado": "Escanteios", "linha": 14.0, "reason": "margin_low", "margin": -0.0198}, {"casa": "7k", "mercado": "Escanteios", "linha": 8.5, "reason": "margin_high_kept", "margin": 0.1343}, {"casa": "7k", "mercado": "Cartões", "linha": 5.5, "reason": "margin_high_kept", "margin": 0.1638}, {"casa": "bet365", "mercado": "Escanteios", "linha": 5.0, "reason": "margin_low", "margin": -0.0074}, {"casa": "bet365", "mercado": "Escanteios", "linha": 6.0, "reason": "margin_low", "margin": -0.0203}, {"casa": "bet365", "mercado": "Escanteios", "linha": 7.0, "reason": "margin_low", "margin": -0.0481}, {"casa": "bet365", "mercado": "Escanteios", "linha": 8.0, "reason": "margin_low", "margin": -0.0554}, {"casa": "bet365", "mercado": "Escanteios", "linha": 10.0, "reason": "margin_low", "margin": -0.0403}, {"casa": "bet365", "mercado": "Escanteios", "linha": 11.0, "reason": "margin_low", "margin": -0.0198}, {"casa": "bet365", "mercado": "Escanteios", "linha": 12.0, "reason": "margin_low", "margin": -0.0188}, {"casa": "bet365", "mercado": "Escanteios", "linha": 13.0, "reason": "margin_low", "margin": -0.0203}, {"casa": "7k", "mercado": "Escanteios", "linha": 9.5, "reason": "margin_high_kept", "margin": 0.1361}, {"casa": "7k", "mercado": "Cartões", "linha": 4.5, "reason": "margin_high_kept", "margin": 0.1648}, {"casa": "bet365", "mercado": "Escanteios", "linha": 5.0, "reason": "margin_low", "margin": -0.0074}, {"casa": "bet365", "mercado": "Escanteios", "linha": 6.0, "reason": "margin_low", "margin": -0.0417}, {"casa": "bet365", "mercado": "Escanteios", "linha": 7.0, "reason": "margin_low", "margin": -0.0338}, {"casa": "bet365", "mercado": "Escanteios", "linha": 8.0, "reason": "margin_low", "margin": -0.0455}, {"casa": "bet365", "mercado": "Escanteios", "linha": 10.0, "reason": "margin_low", "margin": -0.0376}, {"casa": "bet365", "mercado": "Escanteios", "linha": 11.0, "reason": "margin_low", "margin": -0.019}, {"casa": "bet365", "mercado": "Escanteios", "linha": 12.0, "reason": "margin_low", "margin": -0.0182}, {"casa": "bet365", "mercado": "Escanteios", "linha": 13.0, "reason": "margin_low", "margin": -0.0117}, {"casa": "7k", "mercado": "Cartões", "linha": 4.5, "reason": "margin_high_kept", "margin": 0.1366}, {"casa": "7k", "mercado": "Escanteios", "linha": 7.5, "reason": "margin_high_kept", "margin": 0.127}, {"casa": "7k", "mercado": "Escanteios", "linha": 8.5, "reason": "margin_high_kept", "margin": 0.1294}, {"casa": "7k", "mercado": "Escanteios", "linha": 9.5, "reason": "margin_high_kept", "margin": 0.1237}, {"casa": "7k", "mercado": "Escanteios", "linha": 10.5, "reason": "margin_high_kept", "margin": 0.1322}, {"casa": "7k", "mercado": "Escanteios", "linha": 11.5, "reason": "margin_high_kept", "margin": 0.1301}, {"casa": "7k", "mercado": "Cartões", "linha": 5.5, "reason": "margin_high_kept", "margin": 0.1381}, {"casa": "7k", "mercado": "Escanteios", "linha": 7.5, "reason": "margin_high_kept", "margin": 0.1281}, {"casa": "7k", "mercado": "Escanteios", "linha": 8.5, "reason": "margin_high_kept", "margin": 0.132}, {"casa": "7k", "mercado": "Escanteios", "linha": 9.5, "reason": "margin_high_kept", "margin": 0.1253}, {"casa": "7k", "mercado": "Escanteios", "linha": 10.5, "reason": "margin_high_kept", "margin": 0.1259}, {"casa": "7k", "mercado": "Escanteios", "linha": 11.5, "reason": "margin_high_kept", "margin": 0.1302}, {"casa": "bet365", "mercado": "Escanteios", "linha": 6.0, "reason": "margin_low", "margin": -0.0074}, {"casa": "bet365", "mercado": "Escanteios", "linha": 7.0, "reason": "margin_low", "margin": -0.0203}, {"casa": "bet365", "mercado": "Escanteios", "linha": 8.0, "reason": "margin_low", "margin": -0.0481}, {"casa": "bet365", "mercado": "Escanteios", "linha": 9.0, "reason": "margin_low", "margin": -0.0387}, {"casa": "bet365", "mercado": "Escanteios", "linha": 11.0, "reason": "margin_low", "margin": -0.0536}, {"casa": "bet365", "mercado": "Escanteios", "linha": 12.0, "reason": "margin_low", "margin": -0.0392}, {"casa": "bet365", "mercado": "Escanteios", "linha": 13.0, "reason": "margin_low", "margin": -0.0085}, {"casa": "bet365", "mercado": "Escanteios", "linha": 5.0, "reason": "margin_low", "margin": -0.014}, {"casa": "bet365", "mercado": "Escanteios", "linha": 6.0, "reason": "margin_low", "margin": -0.0238}, {"casa": "bet365", "mercado": "Escanteios", "linha": 7.0, "reason": "margin_low", "margin": -0.0338}, {"casa": "bet365", "mercado": "Escanteios", "linha": 8.0, "reason": "margin_low", "margin": -0.0679}, {"casa": "bet365", "mercado": "Escanteios", "linha": 10.0, "reason": "margin_low", "margin": -0.0376}, {"casa": "bet365", "mercado": "Escanteios", "linha": 11.0, "reason": "margin_low", "margin": -0.0357}, {"casa": "bet365", "mercado": "Escanteios", "linha": 12.0, "reason": "margin_low", "margin": -0.0137}, {"casa": "bet365", "mercado": "Escanteios", "linha": 5.0, "reason": "margin_low", "margin": -0.0074}, {"casa": "bet365", "mercado": "Escanteios", "linha": 6.0, "reason": "margin_low", "margin": -0.0417}, {"casa": "bet365", "mercado": "Escanteios", "linha": 7.0, "reason": "margin_low", "margin": -0.0338}, {"casa": "bet365", "mercado": "Escanteios", "linha": 8.0, "reason": "margin_low", "margin": -0.0455}, {"casa": "bet365", "mercado": "Escanteios", "linha": 10.0, "reason": "margin_low", "margin": -0.0376}, {"casa": "bet365", "mercado": "Escanteios", "linha": 11.0, "reason": "margin_low", "margin": -0.019}, {"casa": "bet365", "mercado": "Escanteios", "linha": 12.0, "reason": "margin_low", "margin": -0.0182}, {"casa": "bet365", "mercado": "Escanteios", "linha": 13.0, "reason": "margin_low", "margin": -0.0117}, {"casa": "bet365", "mercado": "Escanteios", "linha": 5.0, "reason": "margin_low", "margin": -0.0074}, {"casa": "bet365", "mercado": "Escanteios", "linha": 6.0, "reason": "margin_low", "margin": -0.0417}, {"casa": "bet365", "mercado": "Escanteios", "linha": 7.0, "reason": "margin_low", "margin": -0.0338}, {"casa": "bet365", "mercado": "Escanteios", "linha": 8.0, "reason": "margin_low", "margin": -0.0455}, {"casa": "bet365", "mercado": "Escanteios", "linha": 10.0, "reason": "margin_low", "margin": -0.0376}, {"casa": "bet365", "mercado": "Escanteios", "linha": 11.0, "reason": "margin_low", "margin": -0.019}, {"casa": "bet365", "mercado": "Escanteios", "linha": 12.0, "reason": "margin_low", "margin": -0.0182}, {"casa": "bet365", "mercado": "Escanteios", "linha": 13.0, "reason": "margin_low", "margin": -0.0117}, {"casa": "bet365", "mercado": "Escanteios", "linha": 4.0, "reason": "margin_low", "margin": -0.0128}, {"casa": "bet365", "mercado": "Escanteios", "linha": 5.0, "reason": "margin_low", "margin": -0.0342}, {"casa": "bet365", "mercado": "Escanteios", "linha": 6.0, "reason": "margin_low", "margin": -0.0481}, {"casa": "bet365", "mercado": "Escanteios", "linha": 7.0, "reason": "margin_low", "margin": -0.0712}, {"casa": "bet365", "mercado": "Escanteios", "linha": 9.0, "reason": "margin_low", "margin": -0.0583}, {"casa": "bet365", "mercado": "Escanteios", "linha": 10.0, "reason": "margin_low", "margin": -0.019}, {"casa": "bet365", "mercado": "Escanteios", "linha": 11.0, "reason": "margin_low", "margin": -0.0182}, {"casa": "bet365", "mercado": "Escanteios", "linha": 12.0, "reason": "margin_low", "margin": -0.0117}, {"casa": "bet365", "mercado": "Escanteios", "linha": 5.0, "reason": "margin_low", "margin": -0.014}, {"casa": "bet365", "mercado": "Escanteios", "linha": 6.0, "reason": "margin_low", "margin": -0.0238}, {"casa": "bet365", "mercado": "Escanteios", "linha": 7.0, "reason": "margin_low", "margin": -0.0548}, {"casa": "bet365", "mercado": "Escanteios", "linha": 8.0, "reason": "margin_low", "margin": -0.0376}, {"casa": "bet365", "mercado": "Escanteios", "linha": 10.0, "reason": "margin_low", "margin": -0.0152}, {"casa": "bet365", "mercado": "Escanteios", "linha": 11.0, "reason": "margin_low", "margin": -0.0357}, {"casa": "bet365", "mercado": "Escanteios", "linha": 12.0, "reason": "margin_low", "margin": -0.0137}, {"casa": "bet365", "mercado": "Escanteios", "linha": 6.0, "reason": "margin_low", "margin": -0.0162}, {"casa": "bet365", "mercado": "Escanteios", "linha": 7.0, "reason": "margin_low", "margin": -0.0137}, {"casa": "bet365", "mercado": "Escanteios", "linha": 8.0, "reason": "margin_low", "margin": -0.0556}, {"casa": "bet365", "mercado": "Escanteios", "linha": 9.0, "reason": "margin_low", "margin": -0.0403}, {"casa": "bet365", "mercado": "Escanteios", "linha": 11.0, "reason": "margin_low", "margin": -0.0152}, {"casa": "bet365", "mercado": "Escanteios", "linha": 12.0, "reason": "margin_low", "margin": -0.0357}, {"casa": "bet365", "mercado": "Escanteios", "linha": 14.0, "reason": "margin_low", "margin": -0.0117}, {"casa": "bet365", "mercado": "Escanteios", "linha": 5.0, "reason": "margin_low", "margin": -0.0074}, {"casa": "bet365", "mercado": "Escanteios", "linha": 6.0, "reason": "margin_low", "margin": -0.0417}, {"casa": "bet365", "mercado": "Escanteios", "linha": 7.0, "reason": "margin_low", "margin": -0.0338}, {"casa": "bet365", "mercado": "Escanteios", "linha": 8.0, "reason": "margin_low", "margin": -0.0679}, {"casa": "bet365", "mercado": "Escanteios", "linha": 10.0, "reason": "margin_low", "margin": -0.0376}, {"casa": "bet365", "mercado": "Escanteios", "linha": 11.0, "reason": "margin_low", "margin": -0.019}, {"casa": "bet365", "mercado": "Escanteios", "linha": 12.0, "reason": "margin_low", "margin": -0.0182}, {"casa": "bet365", "mercado": "Escanteios", "linha": 13.0, "reason": "margin_low", "margin": -0.0117}, {"casa": "bet365", "mercado": "Escanteios", "linha": 6.0, "reason": "margin_low", "margin": -0.0228}, {"casa": "bet365", "mercado": "Escanteios", "linha": 7.0, "reason": "margin_low", "margin": -0.0369}, {"casa": "bet365", "mercado": "Escanteios", "linha": 8.0, "reason": "margin_low", "margin": -0.0476}, {"casa": "bet365", "mercado": "Escanteios", "linha": 9.0, "reason": "margin_low", "margin": -0.0536}, {"casa": "bet365", "mercado": "Escanteios", "linha": 11.0, "reason": "margin_low", "margin": -0.0523}, {"casa": "bet365", "mercado": "Escanteios", "linha": 12.0, "reason": "margin_low", "margin": -0.0085}, {"casa": "7k", "mercado": "Cartões", "linha": 5.5, "reason": "margin_high_kept", "margin": 0.1691}, {"casa": "7k", "mercado": "Escanteios", "linha": 8.5, "reason": "margin_high_kept", "margin": 0.1429}, {"casa": "7k", "mercado": "Escanteios", "linha": 8.5, "reason": "margin_high_kept", "margin": 0.12}, {"casa": "7k", "mercado": "Cartões", "linha": 5.0, "reason": "margin_high_kept", "margin": 0.1212}, {"casa": "7k", "mercado": "Cartões", "linha": 5.0, "reason": "margin_high_kept", "margin": 0.1265}, {"casa": "7k", "mercado": "Cartões", "linha": 5.5, "reason": "margin_high_kept", "margin": 0.1242}, {"casa": "7k", "mercado": "Cartões", "linha": 5.5, "reason": "margin_high_kept", "margin": 0.1251}, {"casa": "7k", "mercado": "Cartões", "linha": 6.0, "reason": "margin_high_kept", "margin": 0.1237}, {"casa": "7k", "mercado": "Cartões", "linha": 6.0, "reason": "margin_high_kept", "margin": 0.1212}, {"casa": "7k", "mercado": "Cartões", "linha": 5.5, "reason": "margin_high_kept", "margin": 0.1224}, {"casa": "7k", "mercado": "Escanteios", "linha": 8.5, "reason": "margin_high_kept", "margin": 0.12}, {"casa": "7k", "mercado": "Cartões", "linha": 4.5, "reason": "margin_high_kept", "margin": 0.1242}, {"casa": "7k", "mercado": "Cartões", "linha": 6.0, "reason": "margin_high_kept", "margin": 0.1212}, {"casa": "7k", "mercado": "Faltas", "linha": 27.5, "reason": "margin_high_kept", "margin": 0.1705}, {"casa": "7k", "mercado": "Cartões", "linha": 5.5, "reason": "margin_high_kept", "margin": 0.1243}, {"casa": "7k", "mercado": "Escanteios", "linha": 8.5, "reason": "margin_high_kept", "margin": 0.1311}, {"casa": "7k", "mercado": "Escanteios", "linha": 9.5, "reason": "margin_high_kept", "margin": 0.1296}, {"casa": "7k", "mercado": "Escanteios", "linha": 10.5, "reason": "margin_high_kept", "margin": 0.1251}, {"casa": "7k", "mercado": "Escanteios", "linha": 11.5, "reason": "margin_high_kept", "margin": 0.1293}, {"casa": "7k", "mercado": "Escanteios", "linha": 12.5, "reason": "margin_high_kept", "margin": 0.1332}, {"casa": "7k", "mercado": "Cartões", "linha": 5.5, "reason": "margin_high_kept", "margin": 0.138}, {"casa": "EstrelaBet", "mercado": "Cartões", "linha": 5.5, "reason": "margin_high_kept", "margin": 0.1474}, {"casa": "7k", "mercado": "Escanteios", "linha": 8.5, "reason": "margin_high_kept", "margin": 0.1301}, {"casa": "7k", "mercado": "Escanteios", "linha": 9.5, "reason": "margin_high_kept", "margin": 0.1283}, {"casa": "7k", "mercado": "Escanteios", "linha": 10.5, "reason": "margin_high_kept", "margin": 0.1236}, {"casa": "7k", "mercado": "Escanteios", "linha": 11.5, "reason": "margin_high_kept", "margin": 0.1328}, {"casa": "7k", "mercado": "Escanteios", "linha": 12.5, "reason": "margin_high_kept", "margin": 0.1322}, {"casa": "7k", "mercado": "Cartões", "linha": 5.0, "reason": "margin_high_kept", "margin": 0.1365}, {"casa": "EstrelaBet", "mercado": "Cartões", "linha": 5.5, "reason": "margin_high_kept", "margin": 0.1329}, {"casa": "7k", "mercado": "Escanteios", "linha": 8.5, "reason": "margin_high_kept", "margin": 0.1302}, {"casa": "7k", "mercado": "Escanteios", "linha": 9.5, "reason": "margin_high_kept", "margin": 0.1318}, {"casa": "7k", "mercado": "Escanteios", "linha": 10.5, "reason": "margin_high_kept", "margin": 0.1224}, {"casa": "7k", "mercado": "Escanteios", "linha": 11.5, "reason": "margin_high_kept", "margin": 0.1311}, {"casa": "7k", "mercado": "Escanteios", "linha": 12.5, "reason": "margin_high_kept", "margin": 0.1295}, {"casa": "7k", "mercado": "Cartões", "linha": 5.0, "reason": "margin_high_kept", "margin": 0.1358}, {"casa": "EstrelaBet", "mercado": "Cartões", "linha": 5.5, "reason": "margin_high_kept", "margin": 0.1327}, {"casa": "7k", "mercado": "Escanteios", "linha": 8.5, "reason": "margin_high_kept", "margin": 0.1292}, {"casa": "7k", "mercado": "Escanteios", "linha": 9.5, "reason": "margin_high_kept", "margin": 0.1289}, {"casa": "7k", "mercado": "Escanteios", "linha": 10.5, "reason": "margin_high_kept", "margin": 0.1211}, {"casa": "7k", "mercado": "Escanteios", "linha": 11.5, "reason": "margin_high_kept", "margin": 0.1314}, {"casa": "7k", "mercado": "Escanteios", "linha": 12.5, "reason": "margin_high_kept", "margin": 0.1285}, {"casa": "7k", "mercado": "Cartões", "linha": 4.5, "reason": "margin_high_kept", "margin": 0.1347}, {"casa": "EstrelaBet", "mercado": "Cartões", "linha": 4.5, "reason": "margin_high_kept", "margin": 0.1336}, {"casa": "7k", "mercado": "Escanteios", "linha": 8.5, "reason": "margin_high_kept", "margin": 0.127}, {"casa": "7k", "mercado": "Escanteios", "linha": 9.5, "reason": "margin_high_kept", "margin": 0.1301}, {"casa": "7k", "mercado": "Escanteios", "linha": 10.5, "reason": "margin_high_kept", "margin": 0.1252}, {"casa": "7k", "mercado": "Escanteios", "linha": 11.5, "reason": "margin_high_kept", "margin": 0.1295}, {"casa": "7k", "mercado": "Escanteios", "linha": 12.5, "reason": "margin_high_kept", "margin": 0.1295}, {"casa": "7k", "mercado": "Cartões", "linha": 5.0, "reason": "margin_high_kept", "margin": 0.1364}, {"casa": "EstrelaBet", "mercado": "Cartões", "linha": 5.5, "reason": "margin_high_kept", "margin": 0.1329}, {"casa": "7k", "mercado": "Escanteios", "linha": 8.5, "reason": "margin_high_kept", "margin": 0.1297}, {"casa": "7k", "mercado": "Escanteios", "linha": 9.5, "reason": "margin_high_kept", "margin": 0.1301}, {"casa": "7k", "mercado": "Escanteios", "linha": 10.5, "reason": "margin_high_kept", "margin": 0.1224}, {"casa": "7k", "mercado": "Escanteios", "linha": 11.5, "reason": "margin_high_kept", "margin": 0.1311}, {"casa": "7k", "mercado": "Escanteios", "linha": 12.5, "reason": "margin_high_kept", "margin": 0.1295}, {"casa": "7k", "mercado": "Cartões", "linha": 6.0, "reason": "margin_high_kept", "margin": 0.1358}, {"casa": "EstrelaBet", "mercado": "Cartões", "linha": 5.5, "reason": "margin_high_kept", "margin": 0.1486}, {"casa": "7k", "mercado": "Escanteios", "linha": 7.5, "reason": "margin_high_kept", "margin": 0.1277}, {"casa": "7k", "mercado": "Escanteios", "linha": 8.5, "reason": "margin_high_kept", "margin": 0.131}, {"casa": "7k", "mercado": "Escanteios", "linha": 9.5, "reason": "margin_high_kept", "margin": 0.1259}, {"casa": "7k", "mercado": "Escanteios", "linha": 10.5, "reason": "margin_high_kept", "margin": 0.1296}, {"casa": "7k", "mercado": "Escanteios", "linha": 11.5, "reason": "margin_high_kept", "margin": 0.1309}, {"casa": "7k", "mercado": "Cartões", "linha": 6.0, "reason": "margin_high_kept", "margin": 0.1358}, {"casa": "EstrelaBet", "mercado": "Cartões", "linha": 6.5, "reason": "margin_high_kept", "margin": 0.1474}, {"casa": "7k", "mercado": "Escanteios", "linha": 8.5, "reason": "margin_high_kept", "margin": 0.1418}, {"casa": "7k", "mercado": "Cartões", "linha": 5.5, "reason": "margin_high_kept", "margin": 0.1695}, {"casa": "7k", "mercado": "Cartões", "linha": 4.0, "reason": "margin_high_kept", "margin": 0.1347}, {"casa": "7k", "mercado": "Escanteios", "linha": 7.5, "reason": "margin_high_kept", "margin": 0.1285}, {"casa": "7k", "mercado": "Escanteios", "linha": 8.5, "reason": "margin_high_kept", "margin": 0.1283}, {"casa": "7k", "mercado": "Escanteios", "linha": 9.5, "reason": "margin_high_kept", "margin": 0.1236}, {"casa": "7k", "mercado": "Escanteios", "linha": 10.5, "reason": "margin_high_kept", "margin": 0.1302}, {"casa": "7k", "mercado": "Escanteios", "linha": 11.5, "reason": "margin_high_kept", "margin": 0.1311}, {"casa": "7k", "mercado": "Cartões", "linha": 5.5, "reason": "margin_high_kept", "margin": 0.1373}, {"casa": "7k", "mercado": "Escanteios", "linha": 8.5, "reason": "margin_high_kept", "margin": 0.1275}, {"casa": "7k", "mercado": "Escanteios", "linha": 9.5, "reason": "margin_high_kept", "margin": 0.1211}, {"casa": "7k", "mercado": "Escanteios", "linha": 10.5, "reason": "margin_high_kept", "margin": 0.1296}, {"casa": "7k", "mercado": "Escanteios", "linha": 11.5, "reason": "margin_high_kept", "margin": 0.1292}, {"casa": "7k", "mercado": "Escanteios", "linha": 12.5, "reason": "margin_high_kept", "margin": 0.1276}, {"casa": "7k", "mercado": "Escanteios", "linha": 7.5, "reason": "margin_high_kept", "margin": 0.127}, {"casa": "7k", "mercado": "Escanteios", "linha": 8.5, "reason": "margin_high_kept", "margin": 0.1283}, {"casa": "7k", "mercado": "Escanteios", "linha": 9.5, "reason": "margin_high_kept", "margin": 0.1236}, {"casa": "7k", "mercado": "Escanteios", "linha": 10.5, "reason": "margin_high_kept", "margin": 0.1283}, {"casa": "7k", "mercado": "Escanteios", "linha": 11.5, "reason": "margin_high_kept", "margin": 0.1289}, {"casa": "7k", "mercado": "Cartões", "linha": 4.5, "reason": "margin_high_kept", "margin": 0.1373}, {"casa": "7k", "mercado": "Escanteios", "linha": 8.5, "reason": "margin_high_kept", "margin": 0.1322}, {"casa": "7k", "mercado": "Escanteios", "linha": 9.5, "reason": "margin_high_kept", "margin": 0.132}, {"casa": "7k", "mercado": "Escanteios", "linha": 10.5, "reason": "margin_high_kept", "margin": 0.1253}, {"casa": "7k", "mercado": "Escanteios", "linha": 11.5, "reason": "margin_high_kept", "margin": 0.1285}, {"casa": "7k", "mercado": "Escanteios", "linha": 12.5, "reason": "margin_high_kept", "margin": 0.127}, {"casa": "7k", "mercado": "Cartões", "linha": 3.5, "reason": "margin_high_kept", "margin": 0.138}, {"casa": "7k", "mercado": "Cartões", "linha": 4.5, "reason": "margin_high_kept", "margin": 0.1365}, {"casa": "7k", "mercado": "Escanteios", "linha": 8.5, "reason": "margin_high_kept", "margin": 0.1326}, {"casa": "7k", "mercado": "Escanteios", "linha": 9.5, "reason": "margin_high_kept", "margin": 0.1328}, {"casa": "7k", "mercado": "Escanteios", "linha": 10.5, "reason": "margin_high_kept", "margin": 0.1242}, {"casa": "7k", "mercado": "Escanteios", "linha": 11.5, "reason": "margin_high_kept", "margin": 0.1322}, {"casa": "7k", "mercado": "Escanteios", "linha": 12.5, "reason": "margin_high_kept", "margin": 0.1354}, {"casa": "7k", "mercado": "Cartões", "linha": 5.5, "reason": "margin_high_kept", "margin": 0.137}, {"casa": "7k", "mercado": "Escanteios", "linha": 7.5, "reason": "margin_high_kept", "margin": 0.1281}, {"casa": "7k", "mercado": "Escanteios", "linha": 8.5, "reason": "margin_high_kept", "margin": 0.132}, {"casa": "7k", "mercado": "Escanteios", "linha": 9.5, "reason": "margin_high_kept", "margin": 0.1253}, {"casa": "7k", "mercado": "Escanteios", "linha": 10.5, "reason": "margin_high_kept", "margin": 0.131}, {"casa": "7k", "mercado": "Escanteios", "linha": 11.5, "reason": "margin_high_kept", "margin": 0.1302}, {"casa": "7k", "mercado": "Escanteios", "linha": 7.5, "reason": "margin_high_kept", "margin": 0.1295}, {"casa": "7k", "mercado": "Escanteios", "linha": 8.5, "reason": "margin_high_kept", "margin": 0.1276}, {"casa": "7k", "mercado": "Escanteios", "linha": 9.5, "reason": "margin_high_kept", "margin": 0.1245}, {"casa": "7k", "mercado": "Escanteios", "linha": 10.5, "reason": "margin_high_kept", "margin": 0.1302}, {"casa": "7k", "mercado": "Escanteios", "linha": 11.5, "reason": "margin_high_kept", "margin": 0.1322}, {"casa": "7k", "mercado": "Cartões", "linha": 4.5, "reason": "margin_high_kept", "margin": 0.1364}, {"casa": "7k", "mercado": "Cartões", "linha": 4.5, "reason": "margin_high_kept", "margin": 0.1364}, {"casa": "7k", "mercado": "Escanteios", "linha": 8.5, "reason": "margin_high_kept", "margin": 0.1324}, {"casa": "7k", "mercado": "Escanteios", "linha": 9.5, "reason": "margin_high_kept", "margin": 0.1324}, {"casa": "7k", "mercado": "Escanteios", "linha": 10.5, "reason": "margin_high_kept", "margin": 0.1252}, {"casa": "7k", "mercado": "Escanteios", "linha": 11.5, "reason": "margin_high_kept", "margin": 0.1332}, {"casa": "7k", "mercado": "Escanteios", "linha": 12.5, "reason": "margin_high_kept", "margin": 0.1277}, {"casa": "7k", "mercado": "Escanteios", "linha": 8.5, "reason": "margin_high_kept", "margin": 0.1293}, {"casa": "7k", "mercado": "Escanteios", "linha": 9.5, "reason": "margin_high_kept", "margin": 0.1296}, {"casa": "7k", "mercado": "Escanteios", "linha": 10.5, "reason": "margin_high_kept", "margin": 0.1211}, {"casa": "7k", "mercado": "Escanteios", "linha": 11.5, "reason": "margin_high_kept", "margin": 0.1306}, {"casa": "7k", "mercado": "Escanteios", "linha": 12.5, "reason": "margin_high_kept", "margin": 0.1283}, {"casa": "7k", "mercado": "Cartões", "linha": 5.5, "reason": "margin_high_kept", "margin": 0.1366}, {"casa": "7k", "mercado": "Escanteios", "linha": 7.5, "reason": "margin_high_kept", "margin": 0.1307}, {"casa": "7k", "mercado": "Escanteios", "linha": 8.5, "reason": "margin_high_kept", "margin": 0.1306}, {"casa": "7k", "mercado": "Escanteios", "linha": 9.5, "reason": "margin_high_kept", "margin": 0.1252}, {"casa": "7k", "mercado": "Escanteios", "linha": 10.5, "reason": "margin_high_kept", "margin": 0.1324}, {"casa": "7k", "mercado": "Escanteios", "linha": 11.5, "reason": "margin_high_kept", "margin": 0.1279}, {"casa": "7k", "mercado": "Cartões", "linha": 5.0, "reason": "margin_high_kept", "margin": 0.1365}, {"casa": "7k", "mercado": "Cartões", "linha": 5.0, "reason": "margin_high_kept", "margin": 0.1358}, {"casa": "7k", "mercado": "Escanteios", "linha": 7.5, "reason": "margin_high_kept", "margin": 0.131}, {"casa": "7k", "mercado": "Escanteios", "linha": 8.5, "reason": "margin_high_kept", "margin": 0.1295}, {"casa": "7k", "mercado": "Escanteios", "linha": 9.5, "reason": "margin_high_kept", "margin": 0.1224}, {"casa": "7k", "mercado": "Escanteios", "linha": 10.5, "reason": "margin_high_kept", "margin": 0.1318}, {"casa": "7k", "mercado": "Escanteios", "linha": 11.5, "reason": "margin_high_kept", "margin": 0.1302}, {"casa": "7k", "mercado": "Cartões", "linha": 4.0, "reason": "margin_high_kept", "margin": 0.1343}, {"casa": "7k", "mercado": "Escanteios", "linha": 8.5, "reason": "margin_high_kept", "margin": 0.1294}, {"casa": "7k", "mercado": "Escanteios", "linha": 9.5, "reason": "margin_high_kept", "margin": 0.1296}, {"casa": "7k", "mercado": "Escanteios", "linha": 10.5, "reason": "margin_high_kept", "margin": 0.1211}, {"casa": "7k", "mercado": "Escanteios", "linha": 11.5, "reason": "margin_high_kept", "margin": 0.1314}, {"casa": "7k", "mercado": "Escanteios", "linha": 12.5, "reason": "margin_high_kept", "margin": 0.1285}, {"casa": "7k", "mercado": "Escanteios", "linha": 7.5, "reason": "margin_high_kept", "margin": 0.1276}, {"casa": "7k", "mercado": "Escanteios", "linha": 8.5, "reason": "margin_high_kept", "margin": 0.1275}, {"casa": "7k", "mercado": "Escanteios", "linha": 9.5, "reason": "margin_high_kept", "margin": 0.1211}, {"casa": "7k", "mercado": "Escanteios", "linha": 10.5, "reason": "margin_high_kept", "margin": 0.1296}, {"casa": "7k", "mercado": "Escanteios", "linha": 11.5, "reason": "margin_high_kept", "margin": 0.1321}, {"casa": "7k", "mercado": "Cartões", "linha": 4.0, "reason": "margin_high_kept", "margin": 0.1343}, {"casa": "7k", "mercado": "Escanteios", "linha": 9.5, "reason": "margin_high_kept", "margin": 0.142}, {"casa": "7k", "mercado": "Cartões", "linha": 5.5, "reason": "margin_high_kept", "margin": 0.1685}, {"casa": "7k", "mercado": "Escanteios", "linha": 7.5, "reason": "margin_high_kept", "margin": 0.1332}, {"casa": "7k", "mercado": "Escanteios", "linha": 8.5, "reason": "margin_high_kept", "margin": 0.1322}, {"casa": "7k", "mercado": "Escanteios", "linha": 9.5, "reason": "margin_high_kept", "margin": 0.1236}, {"casa": "7k", "mercado": "Escanteios", "linha": 10.5, "reason": "margin_high_kept", "margin": 0.1294}, {"casa": "7k", "mercado": "Escanteios", "linha": 11.5, "reason": "margin_high_kept", "margin": 0.1281}, {"casa": "7k", "mercado": "Cartões", "linha": 4.5, "reason": "margin_high_kept", "margin": 0.1377}, {"casa": "7k", "mercado": "Escanteios", "linha": 8.5, "reason": "margin_high_kept", "margin": 0.1278}, {"casa": "7k", "mercado": "Escanteios", "linha": 9.5, "reason": "margin_high_kept", "margin": 0.1223}, {"casa": "7k", "mercado": "Escanteios", "linha": 10.5, "reason": "margin_high_kept", "margin": 0.1301}, {"casa": "7k", "mercado": "Escanteios", "linha": 11.5, "reason": "margin_high_kept", "margin": 0.1275}, {"casa": "7k", "mercado": "Escanteios", "linha": 12.5, "reason": "margin_high_kept", "margin": 0.1318}, {"casa": "7k", "mercado": "Cartões", "linha": 5.0, "reason": "margin_high_kept", "margin": 0.1343}, {"casa": "7k", "mercado": "Cartões", "linha": 4.5, "reason": "margin_high_kept", "margin": 0.1385}, {"casa": "7k", "mercado": "Escanteios", "linha": 7.5, "reason": "margin_high_kept", "margin": 0.1291}, {"casa": "7k", "mercado": "Escanteios", "linha": 8.5, "reason": "margin_high_kept", "margin": 0.1275}, {"casa": "7k", "mercado": "Escanteios", "linha": 9.5, "reason": "margin_high_kept", "margin": 0.1211}, {"casa": "7k", "mercado": "Escanteios", "linha": 10.5, "reason": "margin_high_kept", "margin": 0.1296}, {"casa": "7k", "mercado": "Escanteios", "linha": 11.5, "reason": "margin_high_kept", "margin": 0.1293}, {"casa": "7k", "mercado": "Escanteios", "linha": 8.5, "reason": "margin_high_kept", "margin": 0.1292}, {"casa": "7k", "mercado": "Escanteios", "linha": 9.5, "reason": "margin_high_kept", "margin": 0.1296}, {"casa": "7k", "mercado": "Escanteios", "linha": 10.5, "reason": "margin_high_kept", "margin": 0.1211}, {"casa": "7k", "mercado": "Escanteios", "linha": 11.5, "reason": "margin_high_kept", "margin": 0.1314}, {"casa": "7k", "mercado": "Escanteios", "linha": 12.5, "reason": "margin_high_kept", "margin": 0.1285}, {"casa": "7k", "mercado": "Cartões", "linha": 4.5, "reason": "margin_high_kept", "margin": 0.1364}, {"casa": "7k", "mercado": "Cartões", "linha": 4.5, "reason": "margin_high_kept", "margin": 0.1347}, {"casa": "7k", "mercado": "Escanteios", "linha": 8.5, "reason": "margin_high_kept", "margin": 0.1293}, {"casa": "7k", "mercado": "Escanteios", "linha": 9.5, "reason": "margin_high_kept", "margin": 0.1324}, {"casa": "7k", "mercado": "Escanteios", "linha": 10.5, "reason": "margin_high_kept", "margin": 0.1211}, {"casa": "7k", "mercado": "Escanteios", "linha": 11.5, "reason": "margin_high_kept", "margin": 0.129}, {"casa": "7k", "mercado": "Escanteios", "linha": 12.5, "reason": "margin_high_kept", "margin": 0.1283}, {"casa": "7k", "mercado": "Escanteios", "linha": 8.5, "reason": "margin_high_kept", "margin": 0.1309}, {"casa": "7k", "mercado": "Escanteios", "linha": 9.5, "reason": "margin_high_kept", "margin": 0.1211}, {"casa": "7k", "mercado": "Escanteios", "linha": 10.5, "reason": "margin_high_kept", "margin": 0.1296}, {"casa": "7k", "mercado": "Escanteios", "linha": 11.5, "reason": "margin_high_kept", "margin": 0.1292}, {"casa": "7k", "mercado": "Escanteios", "linha": 12.5, "reason": "margin_high_kept", "margin": 0.1291}, {"casa": "7k", "mercado": "Cartões", "linha": 5.5, "reason": "margin_high_kept", "margin": 0.1352}, {"casa": "7k", "mercado": "Escanteios", "linha": 9.5, "reason": "margin_high_kept", "margin": 0.1438}, {"casa": "7k", "mercado": "Escanteios", "linha": 8.5, "reason": "margin_high_kept", "margin": 0.1447}, {"casa": "7k", "mercado": "Cartões", "linha": 5.5, "reason": "margin_high_kept", "margin": 0.1361}, {"casa": "7k", "mercado": "Cartões", "linha": 5.5, "reason": "margin_high_kept", "margin": 0.1364}, {"casa": "7k", "mercado": "Escanteios", "linha": 7.5, "reason": "margin_high_kept", "margin": 0.1295}, {"casa": "7k", "mercado": "Escanteios", "linha": 8.5, "reason": "margin_high_kept", "margin": 0.1276}, {"casa": "7k", "mercado": "Escanteios", "linha": 9.5, "reason": "margin_high_kept", "margin": 0.1249}, {"casa": "7k", "mercado": "Escanteios", "linha": 10.5, "reason": "margin_high_kept", "margin": 0.1302}, {"casa": "7k", "mercado": "Escanteios", "linha": 11.5, "reason": "margin_high_kept", "margin": 0.1322}, {"casa": "7k", "mercado": "Cartões", "linha": 5.5, "reason": "margin_high_kept", "margin": 0.1358}, {"casa": "7k", "mercado": "Cartões", "linha": 5.0, "reason": "margin_high_kept", "margin": 0.1358}, {"casa": "7k", "mercado": "Escanteios", "linha": 7.5, "reason": "margin_high_kept", "margin": 0.1226}, {"casa": "7k", "mercado": "Escanteios", "linha": 8.5, "reason": "margin_high_kept", "margin": 0.1216}, {"casa": "7k", "mercado": "Escanteios", "linha": 10.5, "reason": "margin_high_kept", "margin": 0.1259}, {"casa": "7k", "mercado": "Escanteios", "linha": 11.5, "reason": "margin_high_kept", "margin": 0.1265}, {"casa": "bet365", "mercado": "Escanteios", "linha": 4.0, "reason": "margin_low", "margin": -0.009}, {"casa": "bet365", "mercado": "Escanteios", "linha": 5.0, "reason": "margin_low", "margin": -0.0228}, {"casa": "bet365", "mercado": "Escanteios", "linha": 6.0, "reason": "margin_low", "margin": -0.0369}, {"casa": "bet365", "mercado": "Escanteios", "linha": 7.0, "reason": "margin_low", "margin": -0.0607}, {"casa": "bet365", "mercado": "Escanteios", "linha": 9.0, "reason": "margin_low", "margin": -0.0628}, {"casa": "bet365", "mercado": "Escanteios", "linha": 10.0, "reason": "margin_low", "margin": -0.0198}, {"casa": "bet365", "mercado": "Escanteios", "linha": 11.0, "reason": "margin_low", "margin": -0.0188}, {"casa": "bet365", "mercado": "Escanteios", "linha": 12.0, "reason": "margin_low", "margin": -0.0203}]}