{
 "casa": "sofa",
 "kind": "fixture",
 "ok": true,
 "ts_utc": "2026-07-19T18:34:30Z",
 "ts_brt": "2026-07-19 15:34",
 "n_events": 145,
 "n_fixtures": 145,
 "n_markets": 0,
 "min_events": 36,
 "promoted": true,
 "pointer_valid": true,
 "pointer_file": "_snapshots/sofa_efccfebe0faccc0fd468.json",
 "pointer_at": "2026-07-19T15:34:30-03:00",
 "pointer_n": 145,
 "pointer_age_h": 0.0,
 "duration_sec": 51.9,
 "error": null,
 "error_class": null,
 "transport": {
  "requests": 39,
  "proxy_attempts": 39,
  "direct_attempts": 0,
  "statuses": {
   "200": 39
  },
  "last_error": null,
  "consecutive_failures": 0,
  "circuit_open": false,
  "failed_tournaments": []
 }
}