{
 "casa": "superbet",
 "ok": true,
 "ts_utc": "2026-07-19T16:08:50Z",
 "ts_brt": "2026-07-19 13:08",
 "n_events": 62,
 "n_markets": 9,
 "market_counts": {
  "Cartões": 20,
  "Chutes no gol": 16,
  "Desarmes": 1,
  "Escanteios": 62,
  "Faltas": 5,
  "Finalizações": 16,
  "Impedimentos": 5,
  "Laterais": 1,
  "Tiros de meta": 1
 },
 "min_events": 10,
 "duration_sec": 75.4,
 "error": null,
 "error_class": null,
 "mode": "full",
 "sample_events": [],
 "proxy_br": true,
 "pointer_valid": true,
 "pointer_file": "superbet_2026-07-19_1307.jsonl",
 "pointer_at": "2026-07-19T13:07:35-03:00",
 "pointer_age_h": 0.021
}