{
 "casa": "superbet",
 "ok": true,
 "ts_utc": "2026-07-19T12:40:39Z",
 "ts_brt": "2026-07-19 09:40",
 "n_events": 31,
 "n_markets": 4,
 "market_counts": {
  "Cartões": 2,
  "Chutes no gol": 1,
  "Escanteios": 31,
  "Finalizações": 1
 },
 "min_events": 1,
 "duration_sec": 24.9,
 "error": null,
 "error_class": null,
 "mode": "close",
 "sample_events": [],
 "proxy_br": true,
 "pointer_valid": true,
 "pointer_file": "superbet_2026-07-19_0940.jsonl",
 "pointer_at": "2026-07-19T09:40:14-03:00",
 "pointer_age_h": 0.007
}